pydo/__init__.py
pydo/_client.py
pydo/_configuration.py
pydo/_patch.py
pydo/_serialization.py
pydo/_version.py
pydo/aio/__init__.py
pydo/aio/_client.py
pydo/aio/_configuration.py
pydo/aio/_patch.py
pydo/aio/operations/__init__.py
pydo/aio/operations/_operations.py
pydo/aio/operations/_patch.py
pydo/custom_policies.py
pydo/exceptions.py
pydo/operations/__init__.py
pydo/operations/_operations.py
pydo/operations/_patch.py
pydo/py.typed
pydo-0.25.0.dist-info/LICENSE
pydo-0.25.0.dist-info/METADATA
pydo-0.25.0.dist-info/WHEEL
pydo-0.25.0.dist-info/RECORD
