Metadata-Version: 2.1
Name: pydo
Version: 0.25.0
Summary: The official client for interacting with the DigitalOcean API
Home-page: https://github.com/digitalocean/pydo
License: Apache-2.0
Keywords: digitalocean,api,client
Author: API Engineering
Author-email: api-engineering@digitalocean.com
Requires-Python: >=3.8.0,<4.0.0
Classifier: Development Status :: 4 - Beta
Classifier: License :: OSI Approved :: Apache Software License
Classifier: Programming Language :: Python :: 3
Classifier: Programming Language :: Python :: 3.8
Classifier: Programming Language :: Python :: 3.9
Classifier: Programming Language :: Python :: 3.10
Classifier: Programming Language :: Python :: 3.11
Classifier: Topic :: Software Development :: Libraries :: Python Modules
Provides-Extra: aio
Requires-Dist: aiohttp (>=3.0) ; extra == "aio"
Requires-Dist: azure-core (>=1.24.0)
Requires-Dist: azure-identity (>=1.5.0)
Requires-Dist: isodate (>=0.6.1)
Requires-Dist: msrest (>=0.7.1)
Requires-Dist: typing-extensions (>=3.7.4)
Project-URL: Documentation, https://pydo.readthedocs.io/
Project-URL: Repository, https://github.com/digitalocean/pydo
